{
    "$schema": "https://schema.management.azure.com/schemas/2015-01-01/deploymentParameters.json#",
    "contentVersion": "1.0.0.0",
    "parameters": {
        "azureFirewallName": {
            "value": "fw-hub-prod"
        },
        "vnet": {
            "value": "vnet-hub-prod-001"
        },
        "zones": {
            "value": []
        },
        "publicIpAddressName": {
            "value": "pip-azfw-hub-prod-001"
        },
        "publicIpZones": {
            "value": []
        }
    }
}